eqword2llm/__init__.py
eqword2llm/cli.py
eqword2llm/constants.py
eqword2llm/converter.py
eqword2llm/math_converter.py
eqword2llm/models.py
eqword2llm/table_converter.py
eqword2llm-0.5.0.dist-info/METADATA
eqword2llm-0.5.0.dist-info/WHEEL
eqword2llm-0.5.0.dist-info/entry_points.txt
eqword2llm-0.5.0.dist-info/licenses/LICENSE
eqword2llm-0.5.0.dist-info/RECORD
