Metadata-Version: 2.4
Name: eqword2llm
Version: 0.5.0
Summary: Convert equation-heavy Word documents (.docx) to Markdown with LaTeX math for LLM recognition.
Project-URL: Homepage, https://github.com/manabelab/eqword2llm
Project-URL: Documentation, https://github.com/manabelab/eqword2llm#readme
Project-URL: Repository, https://github.com/manabelab/eqword2llm.git
Project-URL: Issues, https://github.com/manabelab/eqword2llm/issues
Author-email: Yusuke Manabe <manabe@example.com>
License-Expression: MIT
License-File: LICENSE
Keywords: ai,converter,docx,equation,latex,llm,markdown,math,omml,word
Classifier: Development Status :: 4 - Beta
Classifier: Environment :: Console
Classifier: Intended Audience :: Developers
Classifier: Intended Audience :: Science/Research
Classifier: License :: OSI Approved :: MIT License
Classifier: Operating System :: OS Independent
Classifier: Programming Language :: Python :: 3
Classifier: Programming Language :: Python :: 3.9
Classifier: Programming Language :: Python :: 3.10
Classifier: Programming Language :: Python :: 3.11
Classifier: Programming Language :: Python :: 3.12
Classifier: Programming Language :: Python :: 3.13
Classifier: Topic :: Scientific/Engineering
Classifier: Topic :: Text Processing :: Markup :: LaTeX
Classifier: Topic :: Text Processing :: Markup :: Markdown
Classifier: Topic :: Utilities
Requires-Python: >=3.9
Provides-Extra: dev
Requires-Dist: mypy>=1.0.0; extra == 'dev'
Requires-Dist: pytest-cov>=4.0.0; extra == 'dev'
Requires-Dist: pytest>=7.0.0; extra == 'dev'
Requires-Dist: ruff>=0.1.0; extra == 'dev'
